SystemVerilog/Dividebyevens_clockdivider/design.sv
module divide_byevens_clockdivider (
  input logic clk,
  input logic resetn,
  output logic div2,
  output logic div4,
  output logic div6);
  
  logic [1:0] count_2;
  logic [2:0] count_4;
  logic [3:0] count_6;
  
  
  //clock divider for 2x
  always_ff @ (posedge clk or negedge resetn) begin
    if(!resetn) begin
      count_2<=0;
      div2<=0;
    end
    else begin
      count_2<=count_2+1;
      if(count_2==2'b01) begin
        div2=~div2;
      end
    end
  end
  
  //clock divider for 4x
  always_ff @ (posedge clk or negedge resetn) begin
    if(!resetn) begin
      count_4<=0;
      div4<=0;
    end
    else begin
      count_4<=count_4+1;
      if(count_4==3'b011) begin
        div4=~div4;
      end
    end
  end
  
  //clock divider for 6x
  always_ff @ (posedge clk or negedge resetn) begin
    if(!resetn) begin
      count_6<=0;
      div6<=0;
    end
    else begin
      count_6<=count_6+1;
      if(count_6==4'b0101) begin
        div6=~div6;
      end
    end
  end
endmodule

SystemVerilog/Dividebyevens_clockdivider/testbench.sv
module tb_clockdivider;
  logic clk;
  logic reset;
  logic div2;
  logic div4;
  logic div6;
  
  divide_byevens_clockdivider DUT (.clk(clk),.resetn(reset),.div2(div2),.div4(div4),.div6(div6));
  
  initial begin
    $dumpfile("dump.vcd");
    $dumpvars(1);
  end
  
  
  initial begin
    clk=0;
    forever #5 clk=~clk;
  end
  
  initial begin
          reset = 0;
        #20; // Wait for a while
        reset = 1;
        #100; // Wait and observe outputs

        // Apply reset and check outputs
        reset = 0;
        #20; // Assert reset
        reset = 1;
        #100; // Wait and observe outputs

        // Apply another reset and check outputs
        reset = 0;
        #20; // Assert reset
        reset = 1;
        #100; // Wait and observe outputs
    
     $finish;
    
    
  end
  
  
  initial begin
    $monitor("Time: %0t, Reset:%b, Input: %b, DIV2: %b, DIV4: %b: DIV6: %b", $time, reset, clk, div2, div4, div6);
  end
endmodule

SystemVerilog/Dividebyevens_clockdivider/dump.vcd
$date
Thu Aug  8 15:50:19 2024
$end
$version
Riviera-PRO Version 2023.04.112.8911
$end
$timescale
1 ns
$end

$scope module tb_clockdivider $end
$var reg 1 ! clk $end
$var reg 1 " reset $end
$var reg 1 # div2 $end
$var reg 1 $ div4 $end
$var reg 1 % div6 $end
$upscope $end

$enddefinitions $end
$dumpvars
0!
0"
0#
0$
0%
$end
#5
1!
#10
0!
#15
1!
#20
1"
0!
#25
1!
#30
0!
#35
1!
1#
#40
0!
#45
1!
#50
0!
#55
1!
1$
#60
0!
#65
1!
#70
0!
#75
1!
0#
1%
#80
0!
#85
1!
#90
0!
#95
1!
#100
0!
#105
1!
#110
0!
#115
1!
1#
#120
0"
0!
0#
0$
0%
#125
1!
#130
0!
#135
1!
#140
1"
0!
#145
1!
#150
0!
#155
1!
1#
#160
0!
#165
1!
#170
0!
#175
1!
1$
#180
0!
#185
1!
#190
0!
#195
1!
0#
1%
#200
0!
#205
1!
#210
0!
#215
1!
#220
0!
#225
1!
#230
0!
#235
1!
1#
#240
0"
0!
0#
0$
0%
#245
1!
#250
0!
#255
1!
#260
1"
0!
#265
1!
#270
0!
#275
1!
1#
#280
0!
#285
1!
#290
0!
#295
1!
1$
#300
0!
#305
1!
#310
0!
#315
1!
0#
1%
#320
0!
#325
1!
#330
0!
#335
1!
#340
0!
#345
1!
#350
0!
#355
1!
1#
